odoo/addons/storage_thumbnail/README.rst
odoo/addons/storage_thumbnail/__init__.py
odoo/addons/storage_thumbnail/__manifest__.py
odoo/addons/storage_thumbnail/data/ir_parameter.xml
odoo/addons/storage_thumbnail/i18n/storage_thumbnail.pot
odoo/addons/storage_thumbnail/migrations/13.0.1.2.0/pre-migration.py
odoo/addons/storage_thumbnail/models/__init__.py
odoo/addons/storage_thumbnail/models/storage_file.py
odoo/addons/storage_thumbnail/models/storage_thumbnail.py
odoo/addons/storage_thumbnail/models/thumbnail_mixin.py
odoo/addons/storage_thumbnail/readme/CONTRIBUTORS.rst
odoo/addons/storage_thumbnail/readme/DESCRIPTION.rst
odoo/addons/storage_thumbnail/security/ir.model.access.csv
odoo/addons/storage_thumbnail/static/description/icon.png
odoo/addons/storage_thumbnail/static/description/index.html
odoo/addons/storage_thumbnail/tests/__init__.py
odoo/addons/storage_thumbnail/tests/models.py
odoo/addons/storage_thumbnail/tests/test_thumbnail.py
odoo/addons/storage_thumbnail/tests/static/akretion-logo.png
odoo/addons/storage_thumbnail/views/storage_thumbnail_view.xml
odoo13_addon_storage_thumbnail-13.0.1.3.1.dist-info/METADATA
odoo13_addon_storage_thumbnail-13.0.1.3.1.dist-info/WHEEL
odoo13_addon_storage_thumbnail-13.0.1.3.1.dist-info/top_level.txt
odoo13_addon_storage_thumbnail-13.0.1.3.1.dist-info/RECORD
