Metadata-Version: 2.1
Name: odoo13-addon-storage-thumbnail
Version: 13.0.1.3.1
Summary: Abstract module that add the possibility to have thumbnail
Home-page: https://github.com/OCA/storage
Author: Akretion, Odoo Community Association (OCA)
Author-email: support@odoo-community.org
License: LGPL-3
Platform: UNKNOWN
Classifier: Programming Language :: Python
Classifier: Framework :: Odoo
Classifier: Framework :: Odoo :: 13.0
Classifier: License :: OSI Approved :: GNU Lesser General Public License v3 (LGPLv3)
Classifier: Development Status :: 5 - Production/Stable
Requires-Python: >=3.5
Requires-Dist: odoo13-addon-storage-file
Requires-Dist: odoo (<13.1dev,>=13.0a)
